setup.py
starwars_ipsum/__init__.py
starwars_ipsum/a_new_hope.txt
starwars_ipsum.egg-info/PKG-INFO
starwars_ipsum.egg-info/SOURCES.txt
starwars_ipsum.egg-info/dependency_links.txt
starwars_ipsum.egg-info/requires.txt
starwars_ipsum.egg-info/top_level.txt