Metadata-Version: 1.1
Name: starwars-ipsum
Version: 0.0.2
Summary: A simple utility that generates placeholder text from Star Wars intros.
Home-page: https://github.com/rukbotto/starwars-ipsum
Author: Jose Miguel Venegas Mendoza
Author-email: jvenegas@rukbottoland.com
License: BSD
Keywords: starwars utilities ipsum
Platform: UNKNOWN
Classifier: Development Status :: 3 - Alpha
Classifier: License :: OSI Approved :: BSD License
Classifier: Programming Language :: Python :: 2.7
Classifier: Topic :: Utilities
